calt/__init__.py
calt/data_loader/__init__.py
calt/data_loader/data_loader.py
calt/data_loader/utils/__init__.py
calt/data_loader/utils/comparison_vis.py
calt/data_loader/utils/data_collator.py
calt/data_loader/utils/format_checker.py
calt/data_loader/utils/preprocessor.py
calt/data_loader/utils/tokenizer.py
calt/dataset_generator/__init__.py
calt/dataset_generator/sagemath/__init__.py
calt/dataset_generator/sagemath/dataset_generator.py
calt/dataset_generator/sagemath/utils/__init__.py
calt/dataset_generator/sagemath/utils/dataset_writer.py
calt/dataset_generator/sagemath/utils/polynomial_sampler.py
calt/dataset_generator/sagemath/utils/statistics_calculator.py
calt/dataset_generator/sympy/__init__.py
calt/dataset_generator/sympy/dataset_generator.py
calt/dataset_generator/sympy/utils/__init__.py
calt/dataset_generator/sympy/utils/dataset_writer.py
calt/dataset_generator/sympy/utils/polynomial_sampler.py
calt/dataset_generator/sympy/utils/single_polynomial_sampler.py
calt/dataset_generator/sympy/utils/statistics_calculator.py
calt/models/__init__.py
calt/models/model.py
calt/trainer/__init__.py
calt/trainer/trainer.py
calt/trainer/utils.py
calt_x-0.3.0.dist-info/METADATA
calt_x-0.3.0.dist-info/WHEEL
calt_x-0.3.0.dist-info/top_level.txt
calt_x-0.3.0.dist-info/RECORD
