Metadata-Version: 2.4
Name: calt-x
Version: 0.3.0
Summary: A library for computational algebra using Transformers
Author-email: Hiroshi Kera <kera.hiroshi@gmail.com>, Yuta Sato <sato.yuta@gmail.com>, Shun Arakawa <shun.arkw@gmail.com>
Project-URL: Source, https://github.com/HiroshiKERA/calt
Project-URL: Issues, https://github.com/HiroshiKERA/calt/issues
Requires-Python: <3.13,>=3.10
Requires-Dist: transformers>=4.49.0
Requires-Dist: omegaconf>=2.3.0
Requires-Dist: torch>=2.6.0
Requires-Dist: wandb>=0.15.11
Requires-Dist: accelerate>=0.29.0
Requires-Dist: joblib>=1.5.0
Requires-Dist: sympy>=1.12
Requires-Dist: IPython>=8.18.1
